src/phat/__init__.py
src/phat/__main__.py
src/phat/api.py
src/phat/encryption.py
src/phat/errors.py
src/phat/shared/drives.py
src/phat/shared/ui.py
phat2fa-1.1.2.dist-info/METADATA
phat2fa-1.1.2.dist-info/WHEEL
phat2fa-1.1.2.dist-info/licenses/LICENSE.txt
phat2fa-1.1.2.dist-info/RECORD
