Metadata-Version: 2.1
Name: phat2fa
Version: 1.1.2
Summary: Simple 2FA system using USB flash drives.
Project-URL: Homepage, https://github.com/iiPythonx/phat
Project-URL: Bug Tracker, https://github.com/iiPythonx/phat/issues
Author-email: iiPython <ben@iipython.cf>
License-File: LICENSE.txt
Classifier: Development Status :: 3 - Alpha
Classifier: Environment :: Console
Classifier: License :: OSI Approved :: MIT License
Classifier: Operating System :: OS Independent
Classifier: Programming Language :: Python :: 3
Classifier: Topic :: Security :: Cryptography
Requires-Python: >=3.9
